supersquares/__init__.py
supersquares/squares.py
supersquares-0.0.3.dist-info/LICENSE
supersquares-0.0.3.dist-info/METADATA
supersquares-0.0.3.dist-info/WHEEL
supersquares-0.0.3.dist-info/top_level.txt
supersquares-0.0.3.dist-info/RECORD
