Metadata-Version: 2.1
Name: supersquares
Version: 0.0.3
Summary: Create Super Bowl squares
Home-page: https://github.com/slpardes/super_squares/
Author: Sammy Pardes
Author-email: sammy.pardes@syr.edu
Classifier: Programming Language :: Python :: 3
Classifier: License :: OSI Approved :: MIT License
Classifier: Operating System :: OS Independent
License-File: LICENSE
